bfan/bfan.json
bfan/bfan.py
bfan-1.0.14.dist-info/METADATA
bfan-1.0.14.dist-info/WHEEL
bfan-1.0.14.dist-info/entry_points.txt
bfan-1.0.14.dist-info/top_level.txt
bfan-1.0.14.dist-info/RECORD
