Metadata-Version: 2.4
Name: bfan
Version: 1.0.14
Summary: Binary Functional Automated Testing Framework - YAML-based testing for executables with background process management, output comparison, and CI/CD integration
Author-email: Piotr Sydow <sydow@wp.pl>
License: MIT
Project-URL: Documentation, https://github.com/yourusername/bfan/blob/main/BFAN_DOCUMENTATION.md
Project-URL: Repository, https://github.com/yourusername/bfan
Project-URL: Issues, https://github.com/yourusername/bfan/issues
Keywords: testing,functional-testing,automation,binary-testing,test-framework,yaml,ci-cd,integration-testing
Classifier: Development Status :: 5 - Production/Stable
Classifier: Intended Audience :: Developers
Classifier: Topic :: Software Development :: Testing
Classifier: Topic :: Software Development :: Quality Assurance
Classifier: Programming Language :: Python :: 3
Classifier: Programming Language :: Python :: 3.6
Classifier: Programming Language :: Python :: 3.7
Classifier: Programming Language :: Python :: 3.8
Classifier: Programming Language :: Python :: 3.9
Classifier: Programming Language :: Python :: 3.10
Classifier: Programming Language :: Python :: 3.11
Classifier: License :: OSI Approved :: MIT License
Classifier: Operating System :: OS Independent
Classifier: Environment :: Console
Requires-Python: >=3.6
Requires-Dist: docopt>=0.6.2
Requires-Dist: mako>=1.1.6
Requires-Dist: pyyaml>=5.1
Requires-Dist: psutil>=5.6.0
